[{"url":"https://aldenbryce.com","status":"up","statusCode":200,"responseTimeMs":88,"checkedAt":"2026-03-15T06:37:33Z"},{"url":"https://dev.aldenbryce.com","status":"down","statusCode":000,"responseTimeMs":5001,"checkedAt":"2026-03-15T06:37:33Z"},{"url":"https://qa.aldenbryce.com","status":"up","statusCode":200,"responseTimeMs":229,"checkedAt":"2026-03-15T06:37:33Z"},{"url":"https://status.aldenbryce.com","status":"up","statusCode":200,"responseTimeMs":69,"checkedAt":"2026-03-15T06:37:33Z"},{"url":"https://dev.status.aldenbryce.com","status":"up","statusCode":200,"responseTimeMs":121,"checkedAt":"2026-03-15T06:37:33Z"},{"url":"https://qa.status.aldenbryce.com","status":"up","statusCode":200,"responseTimeMs":108,"checkedAt":"2026-03-15T06:37:33Z"}]
