[{"url":"https://aldenbryce.com","status":"up","statusCode":200,"responseTimeMs":179,"checkedAt":"2026-03-21T09:48:57Z"},{"url":"https://dev.aldenbryce.com","status":"up","statusCode":200,"responseTimeMs":126,"checkedAt":"2026-03-21T09:48:57Z"},{"url":"https://qa.aldenbryce.com","status":"up","statusCode":200,"responseTimeMs":178,"checkedAt":"2026-03-21T09:48:57Z"},{"url":"https://status.aldenbryce.com","status":"up","statusCode":200,"responseTimeMs":91,"checkedAt":"2026-03-21T09:48:57Z"},{"url":"https://dev.status.aldenbryce.com","status":"up","statusCode":200,"responseTimeMs":232,"checkedAt":"2026-03-21T09:48:57Z"},{"url":"https://qa.status.aldenbryce.com","status":"up","statusCode":200,"responseTimeMs":142,"checkedAt":"2026-03-21T09:48:57Z"}]
