[{"url":"https://aldenbryce.com","status":"up","statusCode":200,"responseTimeMs":91,"checkedAt":"2026-03-13T16:54:30Z"},{"url":"https://dev.aldenbryce.com","status":"up","statusCode":200,"responseTimeMs":93,"checkedAt":"2026-03-13T16:54:30Z"},{"url":"https://qa.aldenbryce.com","status":"up","statusCode":200,"responseTimeMs":150,"checkedAt":"2026-03-13T16:54:30Z"},{"url":"https://status.aldenbryce.com","status":"up","statusCode":200,"responseTimeMs":77,"checkedAt":"2026-03-13T16:54:30Z"},{"url":"https://dev.status.aldenbryce.com","status":"up","statusCode":200,"responseTimeMs":99,"checkedAt":"2026-03-13T16:54:30Z"},{"url":"https://qa.status.aldenbryce.com","status":"up","statusCode":200,"responseTimeMs":97,"checkedAt":"2026-03-13T16:54:30Z"}]
